am_num2word/__init__.py
am_num2word/group.py
tests/__init__.py
tests/number_converter.py
am_num2word-0.0.2.dist-info/METADATA
am_num2word-0.0.2.dist-info/WHEEL
am_num2word-0.0.2.dist-info/top_level.txt
am_num2word-0.0.2.dist-info/RECORD
